sscred/__init__.py
sscred/acl.py
sscred/blind_pedersen.py
sscred/blind_signature.py
sscred/commitment.py
sscred/config.py
sscred/pack.py
sscred-0.2.1.dist-info/LICENSE
sscred-0.2.1.dist-info/METADATA
sscred-0.2.1.dist-info/WHEEL
sscred-0.2.1.dist-info/top_level.txt
sscred-0.2.1.dist-info/RECORD
