Metadata-Version: 2.1
Name: sscred
Version: 0.2.1
Summary: Single Show Credentials: A Python library for anonymous authentication.
Home-page: https://github.com/spring-epfl/SSCred
Author: Kasra EdalatNejad
Author-email: kasra.edalat@epfl.ch
License: BSD-3-Clause
Platform: UNKNOWN
Classifier: Intended Audience :: Developers
Classifier: Natural Language :: English
Classifier: Programming Language :: Python
Classifier: Programming Language :: Python :: 3
Classifier: Programming Language :: Python :: 3.6
Classifier: Programming Language :: Python :: 3.7
Classifier: Programming Language :: Python :: 3.8
Classifier: Programming Language :: Python :: 3.9
Classifier: Topic :: Software Development :: Libraries :: Python Modules
Classifier: Topic :: Security :: Cryptography
Classifier: License :: OSI Approved :: BSD License
Requires-Dist: attrs
Requires-Dist: petlib
Requires-Dist: zksk
Provides-Extra: test
Requires-Dist: pytest ; extra == 'test'
